llm_gh_pr.py
llm_gh_pr-0.1.1.dist-info/licenses/LICENSE
llm_gh_pr-0.1.1.dist-info/METADATA
llm_gh_pr-0.1.1.dist-info/WHEEL
llm_gh_pr-0.1.1.dist-info/entry_points.txt
llm_gh_pr-0.1.1.dist-info/top_level.txt
llm_gh_pr-0.1.1.dist-info/RECORD
