Metadata-Version: 2.4
Name: llm-gh-pr
Version: 0.1.1
Summary: LLM plugin to generate GitHub PR titles/bodies and create PRs using the 'gh' CLI.
Author-email: shamanic <shamanicbeatbox@gmail.com>
License: Apache-2.0
Project-URL: Homepage, https://github.com/shamanicarts/llm-gh-pr
Project-URL: Issues, https://github.com/shamanicarts/llm-gh-pr/issues
Classifier: License :: OSI Approved :: Apache Software License
Requires-Python: >=3.8
License-File: LICENSE
Requires-Dist: llm
Requires-Dist: click
Requires-Dist: prompt-toolkit
Dynamic: license-file
